ssb_datahub/__init__.py
ssb_datahub/_adapter/data_service.py
ssb_datahub/_adapter/metadata_service.py
ssb_datahub/_config/environment.py
ssb_datahub/exceptions/__init__.py
ssb_datahub-0.1.3.dist-info/LICENSE
ssb_datahub-0.1.3.dist-info/METADATA
ssb_datahub-0.1.3.dist-info/WHEEL
ssb_datahub-0.1.3.dist-info/RECORD
