Metadata-Version: 2.1
Name: ssb-datahub
Version: 0.1.3
Summary: Client for the SSB datahub platform
License: MIT
Author: Your Name
Author-email: you@example.com
Requires-Python: >=3.10,<4.0
Classifier: License :: OSI Approved :: MIT License
Classifier: Programming Language :: Python :: 3
Classifier: Programming Language :: Python :: 3.10
Classifier: Programming Language :: Python :: 3.11
Requires-Dist: pandas (>=2.0.3,<3.0.0)
Requires-Dist: pyarrow (>=12.0.1,<13.0.0)
Requires-Dist: pydantic (>=2.0.3,<3.0.0)
Requires-Dist: requests (>=2.31.0,<3.0.0)
